scripts/__init__.py
scripts/converter_hf_to_mcore.py
scripts/diagnose.py
scripts/init_random_model.py
scripts/legacy_model_merger.py
scripts/print_cfg.py
scripts/rollout_viewer.py
tests/__init__.py
tests/test_base_config_on_cpu.py
tests/test_protocol_on_cpu.py
tests/test_protocol_v2_on_cpu.py
tests/interactions/__init__.py
tests/interactions/test_gsm8k_interaction.py
tests/interactions/test_interaction_registry.py
tests/single_controller/__init__.py
tests/single_controller/test_auto_padding_on_cpu.py
tests/single_controller/test_colocated_workers.py
tests/single_controller/test_colocated_workers_fused.py
tests/single_controller/test_data_transfer.py
tests/single_controller/test_decorator_on_cpu.py
tests/single_controller/test_device_mesh_register.py
tests/single_controller/test_driverfunc_to_worker.py
tests/single_controller/test_fused_workers_on_cpu.py
tests/single_controller/test_high_level_scheduling_api.py
tests/single_controller/test_nested_worker.py
tests/single_controller/test_ray_collectives.py
tests/single_controller/test_ray_local_envs_on_cpu.py
tests/single_controller/test_ray_utils_on_cpu.py
tests/single_controller/test_rvdz.py
tests/single_controller/test_worker_group_basics.py
tests/single_controller/test_worker_group_torch.py
tests/special_e2e/__init__.py
tests/special_e2e/check_custom_rwd_fn.py
tests/special_e2e/check_results.py
tests/special_e2e/envs/__init__.py
tests/special_e2e/envs/digit_completion/__init__.py
tests/special_e2e/envs/digit_completion/task.py
tests/special_e2e/envs/digit_completion/tokenizer.py
tests/trainer/__init__.py
tests/trainer/config/__init__.py
tests/trainer/config/test_algo_config_on_cpu.py
tests/trainer/config/test_legacy_config_on_cpu.py
tests/trainer/ppo/__init__.py
tests/trainer/ppo/test_core_algos_on_cpu.py
tests/trainer/ppo/test_metric_utils_on_cpu.py
tests/trainer/ppo/test_rollout_corr.py
tests/trainer/ppo/test_rollout_corr_integration.py
verl/__init__.py
verl/base_config.py
verl/protocol.py
verl/py.typed
verl-0.6.1.dist-info/licenses/LICENSE
verl-0.6.1.dist-info/METADATA
verl-0.6.1.dist-info/WHEEL
verl-0.6.1.dist-info/top_level.txt
verl-0.6.1.dist-info/RECORD
